odoo/addons/sale_order_line_client_order_ref/README.rst
odoo/addons/sale_order_line_client_order_ref/__init__.py
odoo/addons/sale_order_line_client_order_ref/__manifest__.py
odoo/addons/sale_order_line_client_order_ref/i18n/ja.po
odoo/addons/sale_order_line_client_order_ref/i18n/sale_order_line_client_order_ref.pot
odoo/addons/sale_order_line_client_order_ref/models/__init__.py
odoo/addons/sale_order_line_client_order_ref/models/account_move_line.py
odoo/addons/sale_order_line_client_order_ref/models/res_company.py
odoo/addons/sale_order_line_client_order_ref/models/res_config_settings.py
odoo/addons/sale_order_line_client_order_ref/models/sale_order_line.py
odoo/addons/sale_order_line_client_order_ref/readme/CONFIGURE.md
odoo/addons/sale_order_line_client_order_ref/readme/CONTRIBUTORS.md
odoo/addons/sale_order_line_client_order_ref/readme/DESCRIPTION.md
odoo/addons/sale_order_line_client_order_ref/reports/report_invoice_document.xml
odoo/addons/sale_order_line_client_order_ref/reports/report_saleorder_document.xml
odoo/addons/sale_order_line_client_order_ref/static/description/icon.png
odoo/addons/sale_order_line_client_order_ref/static/description/index.html
odoo/addons/sale_order_line_client_order_ref/tests/__init__.py
odoo/addons/sale_order_line_client_order_ref/tests/test_sale_order_line_client_order_ref.py
odoo/addons/sale_order_line_client_order_ref/views/account_move_views.xml
odoo/addons/sale_order_line_client_order_ref/views/res_config_settings_views.xml
odoo/addons/sale_order_line_client_order_ref/views/sale_order_views.xml
odoo_addon_sale_order_line_client_order_ref-18.0.1.0.1.dist-info/METADATA
odoo_addon_sale_order_line_client_order_ref-18.0.1.0.1.dist-info/WHEEL
odoo_addon_sale_order_line_client_order_ref-18.0.1.0.1.dist-info/top_level.txt
odoo_addon_sale_order_line_client_order_ref-18.0.1.0.1.dist-info/RECORD
