Metadata-Version: 2.1
Name: odoo-addon-sale_order_line_client_order_ref
Version: 18.0.1.0.1
Requires-Python: >=3.10
Requires-Dist: odoo==18.0.*
Summary: Customer Reference on Sale Order Lines and Invoice Lines
Home-page: https://github.com/OCA/sale-workflow
License: AGPL-3
Author: Quartile, Odoo Community Association (OCA)
Author-email: support@odoo-community.org
Classifier: Programming Language :: Python
Classifier: Framework :: Odoo
Classifier: Framework :: Odoo :: 18.0
Classifier: License :: OSI Approved :: GNU Affero General Public License v3
